scierra/__init__.py
scierra/scierra.py
scierra/compile/__init__.py
scierra/compile/compile.py
scierra/sim/__init__.py
scierra/sim/sim.py
scierra/utils/__init__.py
scierra/utils/utils.py
scierra-0.6.1.dist-info/LICENSE
scierra-0.6.1.dist-info/METADATA
scierra-0.6.1.dist-info/WHEEL
scierra-0.6.1.dist-info/entry_points.txt
scierra-0.6.1.dist-info/top_level.txt
scierra-0.6.1.dist-info/RECORD
