Metadata-Version: 2.1
Name: scierra
Version: 0.6.1
Summary: A Simulated C++ Interpreter
Home-page: https://github.com/PerceptronV/scierra
Author: PerceptronV
Author-email: neutrinovs@gmail.com
License: UNKNOWN
Platform: UNKNOWN
Classifier: Programming Language :: Python :: 3
Classifier: Intended Audience :: Developers
Classifier: Operating System :: OS Independent
Classifier: License :: OSI Approved :: Apache Software License
Classifier: Topic :: Software Development :: Interpreters
Classifier: Development Status :: 4 - Beta
Classifier: Natural Language :: English
Requires-Python: >=3.3
